redel/__init__.py
redel/__main__.py
redel/_version.py
redel/app.py
redel/base_kani.py
redel/config.py
redel/embeddings.py
redel/eventlogger.py
redel/events.py
redel/kanis.py
redel/namer.py
redel/state.py
redel/tool_config.py
redel/utils.py
redel/delegation/__init__.py
redel/delegation/_base.py
redel/delegation/delegate_and_wait.py
redel/delegation/delegate_one.py
redel/server/.gitignore
redel/server/README.md
redel/server/__init__.py
redel/server/__main__.py
redel/server/indexer.py
redel/server/models.py
redel/server/server.py
redel/server/session_manager.py
redel/server/viz_dist/404.html
redel/server/viz_dist/index.html
redel/server/viz_dist/assets/1f916-20e5f946.svg
redel/server/viz_dist/assets/1f9d1-200d-1f4bb-a5e4ed8f.svg
redel/server/viz_dist/assets/index-7cff5d1f.css
redel/server/viz_dist/assets/index-e03bd115.js
redel/tools/__init__.py
redel/tools/_base.py
redel/tools/email.py
redel/tools/browsing/__init__.py
redel/tools/browsing/impl.py
redel/tools/browsing/webutils.py
redel-0.0.2.dist-info/METADATA
redel-0.0.2.dist-info/WHEEL
redel-0.0.2.dist-info/licenses/LICENSE
redel-0.0.2.dist-info/RECORD
