Metadata-Version: 2.3
Name: redel
Version: 0.0.2
Summary: A toolkit for recursive delegation of LLMs
Project-URL: Homepage, https://github.com/zhudotexe/redel
Project-URL: Bug Tracker, https://github.com/zhudotexe/redel/issues
Author-email: Andrew Zhu <andrew@zhu.codes>
License: MIT License
License-File: LICENSE
Classifier: Intended Audience :: Science/Research
Classifier: License :: OSI Approved :: MIT License
Classifier: Operating System :: OS Independent
Classifier: Programming Language :: Python :: 3
Classifier: Topic :: Scientific/Engineering :: Artificial Intelligence
Requires-Python: >=3.10
Requires-Dist: kani-ratelimits
Requires-Dist: kani<2.0.0,>=1.1.0
Requires-Dist: pydantic<3.0.0,>=2.0.0
Requires-Dist: rapidfuzz<4.0.0,>=3.9.0
Provides-Extra: all
Requires-Dist: fastapi<1.0.0,>=0.110.0; extra == 'all'
Requires-Dist: httpx<1.0.0,>=0.23.0; extra == 'all'
Requires-Dist: kani[anthropic,openai]; extra == 'all'
Requires-Dist: numpy<2.0.0,>=1.26.0; extra == 'all'
Requires-Dist: playwright<2.0.0,>=1.43.0; extra == 'all'
Requires-Dist: pymupdf4llm~=0.0.1; extra == 'all'
Requires-Dist: pymupdf<2.0.0,>=1.24.3; extra == 'all'
Requires-Dist: trafilatura<2.0.0,>=1.9.0; extra == 'all'
Requires-Dist: uvicorn~=0.23.2; extra == 'all'
Requires-Dist: websockets~=11.0.3; extra == 'all'
Provides-Extra: bundled
Requires-Dist: httpx<1.0.0,>=0.23.0; extra == 'bundled'
Requires-Dist: kani[anthropic,openai]; extra == 'bundled'
Requires-Dist: numpy<2.0.0,>=1.26.0; extra == 'bundled'
Requires-Dist: playwright<2.0.0,>=1.43.0; extra == 'bundled'
Requires-Dist: pymupdf4llm~=0.0.1; extra == 'bundled'
Requires-Dist: pymupdf<2.0.0,>=1.24.3; extra == 'bundled'
Requires-Dist: trafilatura<2.0.0,>=1.9.0; extra == 'bundled'
Provides-Extra: web
Requires-Dist: fastapi<1.0.0,>=0.110.0; extra == 'web'
Requires-Dist: uvicorn~=0.23.2; extra == 'web'
Requires-Dist: websockets~=11.0.3; extra == 'web'
